bdt/__init__.py
bdt/calibration.py
bdt/cli.py
bdt/lattice.py
bdt/model.py
bdt/pricing.py
bdt/py.typed
bdt/utils.py
bdt_short_rate-1.0.0.dist-info/licenses/LICENSE
bdt_short_rate-1.0.0.dist-info/METADATA
bdt_short_rate-1.0.0.dist-info/WHEEL
bdt_short_rate-1.0.0.dist-info/entry_points.txt
bdt_short_rate-1.0.0.dist-info/top_level.txt
bdt_short_rate-1.0.0.dist-info/RECORD
