Metadata-Version: 2.4
Name: bdt-short-rate
Version: 1.0.0
Summary: Black-Derman-Toy binomial short-rate model for interest rate derivatives
Author-email: Quant Finance Team <quant@example.com>
Maintainer-email: Quant Finance Team <quant@example.com>
License: MIT
Project-URL: Homepage, https://github.com/quantfinance/bdt-short-rate
Project-URL: Documentation, https://bdt-short-rate.readthedocs.io
Project-URL: Repository, https://github.com/quantfinance/bdt-short-rate.git
Project-URL: Issues, https://github.com/quantfinance/bdt-short-rate/issues
Project-URL: Changelog, https://github.com/quantfinance/bdt-short-rate/blob/main/CHANGELOG.md
Keywords: finance,quantitative-finance,interest-rate,short-rate-model,bdt,black-derman-toy,derivatives,swaption,calibration,binomial-tree
Classifier: Development Status :: 4 - Beta
Classifier: Intended Audience :: Financial and Insurance Industry
Classifier: Intended Audience :: Science/Research
Classifier: License :: OSI Approved :: MIT License
Classifier: Operating System :: OS Independent
Classifier: Programming Language :: Python :: 3
Classifier: Programming Language :: Python :: 3.8
Classifier: Programming Language :: Python :: 3.9
Classifier: Programming Language :: Python :: 3.10
Classifier: Programming Language :: Python :: 3.11
Classifier: Programming Language :: Python :: 3.12
Classifier: Topic :: Office/Business :: Financial
Classifier: Topic :: Scientific/Engineering :: Mathematics
Requires-Python: >=3.8
License-File: LICENSE
Requires-Dist: numpy>=1.20.0
Requires-Dist: scipy>=1.7.0
Requires-Dist: pandas>=1.3.0
Provides-Extra: dev
Requires-Dist: pytest>=7.0.0; extra == "dev"
Requires-Dist: pytest-cov>=4.0.0; extra == "dev"
Requires-Dist: black>=23.0.0; extra == "dev"
Requires-Dist: isort>=5.12.0; extra == "dev"
Requires-Dist: mypy>=1.0.0; extra == "dev"
Requires-Dist: flake8>=6.0.0; extra == "dev"
Provides-Extra: docs
Requires-Dist: sphinx>=6.0.0; extra == "docs"
Requires-Dist: sphinx-rtd-theme>=1.2.0; extra == "docs"
Dynamic: license-file
